setup.py
csp_twisted/__init__.py
csp_twisted/port.py
csp_twisted/resource.py
csp_twisted/session.py
csp_twisted/util.py
csp_twisted.egg-info/PKG-INFO
csp_twisted.egg-info/SOURCES.txt
csp_twisted.egg-info/dependency_links.txt
csp_twisted.egg-info/top_level.txt
csp_twisted.egg-info/zip-safe